onepassword_utils/__init__.py
onepassword_utils/onepassword_utils.py
onepassword_utils-0.0.1.dist-info/LICENSE
onepassword_utils-0.0.1.dist-info/METADATA
onepassword_utils-0.0.1.dist-info/WHEEL
onepassword_utils-0.0.1.dist-info/top_level.txt
onepassword_utils-0.0.1.dist-info/RECORD
