Metadata-Version: 2.1
Name: onepassword_utils
Version: 0.0.1
Summary: A collection of utility functions for interacting with 1Password
Home-page: https://github.com/tuklu/Onepassword_Utils.git
Author: Jisnu Kalita
Author-email: jisnukalita@outlook.com
Classifier: Programming Language :: Python :: 3
Classifier: License :: OSI Approved :: MIT License
Classifier: Operating System :: OS Independent
Requires-Python: >=3.6
License-File: LICENSE
Requires-Dist: op
